atlas_compute/__init__.py
atlas_compute/compute.py
atlas_compute/repositories/__init__.py
atlas_compute/repositories/requests_repo.py
atlas_compute-0.1.13.dist-info/METADATA
atlas_compute-0.1.13.dist-info/WHEEL
atlas_compute-0.1.13.dist-info/top_level.txt
atlas_compute-0.1.13.dist-info/RECORD
