Metadata-Version: 2.4
Name: atlas-compute
Version: 0.1.13
Summary: Atlas Compute SDK
Home-page: https://github.com/coreoutline/atlas-compute
Author: Thomas Tsuma
Author-email: tommytsuma7@gmail.com
Classifier: Programming Language :: Python :: 3
Classifier: License :: OSI Approved :: MIT License
Classifier: Operating System :: OS Independent
Requires-Python: >=3.11
Requires-Dist: pandas
Requires-Dist: numpy
Requires-Dist: clickhouse-driver
Requires-Dist: matplotlib
Requires-Dist: opensearch-py
Requires-Dist: minio
Requires-Dist: requests
Requires-Dist: python-dotenv
Dynamic: author
Dynamic: author-email
Dynamic: classifier
Dynamic: description
Dynamic: description-content-type
Dynamic: home-page
Dynamic: requires-dist
Dynamic: requires-python
Dynamic: summary
